lanelet2.libs/liblanelet2_io-b43222d7.so
lanelet2.libs/liblanelet2_routing-30b4e41c.so
lanelet2.libs/liblanelet2_projection-96d4a778.so
lanelet2.libs/liblanelet2_core-83a96f62.so
lanelet2.libs/libboost_filesystem-9c6fc1e5.so.1.75.0
lanelet2.libs/liblanelet2_traffic_rules-4842b695.so
lanelet2.libs/libboost_serialization-7f8b48e5.so.1.75.0
lanelet2.libs/libboost_python39-a897935c.so.1.75.0
lanelet2.libs/liblanelet2_matching-c86b91df.so
lanelet2/core.so
lanelet2/__init__.py
lanelet2/geometry.so
lanelet2/routing.so
lanelet2/projection.so
lanelet2/traffic_rules.so
lanelet2/matching.so
lanelet2/io.so
lanelet2-1.2.2.dist-info/top_level.txt
lanelet2-1.2.2.dist-info/RECORD
lanelet2-1.2.2.dist-info/METADATA
lanelet2-1.2.2.dist-info/WHEEL
