Metadata-Version: 2.1
Name: lanelet2
Version: 1.2.2
Summary: Map handling framework for automated driving.
Home-page: https://github.com/fzi-forschungszentrum-informatik/Lanelet2
Maintainer: Fabian Immel
Maintainer-email: fabian.immel@kit.edu
License: UNKNOWN
Download-URL: https://github.com/fzi-forschungszentrum-informatik/Lanelet2/releases/tag/1.2.2
Platform: UNKNOWN
Classifier: Development Status :: 5 - Production/Stable
Classifier: License :: OSI Approved :: BSD License
Classifier: Operating System :: Unix
Classifier: Programming Language :: Python :: 3
Classifier: Programming Language :: C++
